Metadata-Version: 2.3
Name: openai-http-proxy
Version: 1.1.0
Summary: "OpenAI HTTP Proxy" is OpenAI-compatible http proxy server for inferencing various LLMs capable of working with Google, Anthropic, OpenAI APIs, local PyTorch inference, etc.
License: MIT License
Keywords: llm,large language models,ai,gpt,openai,proxy,http,proxy-server
Author: Vitalii Stepanenko
Author-email: mail@vitalii.in
Maintainer: Vitalii Stepanenko
Maintainer-email: mail@vitalii.in
Requires-Python: >=3.11,<4
Classifier: Intended Audience :: Developers
Classifier: Operating System :: OS Independent
Classifier: Programming Language :: Python :: 3
Classifier: Programming Language :: Python :: 3.11
Classifier: Programming Language :: Python :: 3.12
Classifier: Programming Language :: Python :: 3.13
Classifier: License :: OSI Approved :: MIT License
Requires-Dist: ai-microcore (>=4.4.3,<4.5.0)
Requires-Dist: fastapi (>=0.116.1,<0.117.0)
Requires-Dist: typer (>=0.16.1)
Requires-Dist: uvicorn (>=0.22.0)
Project-URL: Source Code, https://github.com/Nayjest/lm-proxy
